README.md
setup.py
kafka_handler/handler.py
kafka_handler/helpers.py
kafka_handler/wrappers.py
kafka_helper_weko.egg-info/PKG-INFO
kafka_helper_weko.egg-info/SOURCES.txt
kafka_helper_weko.egg-info/dependency_links.txt
kafka_helper_weko.egg-info/requires.txt
kafka_helper_weko.egg-info/top_level.txt