Metadata-Version: 2.1
Name: kafka-helper-weko
Version: 0.0.3
Summary: Kafka handler
Home-page: https://github.com/pypa/sampleproject
Author: Yahor Krautsevich
Author-email: y.krautsevich@gmail.com
License: UNKNOWN
Platform: UNKNOWN
Classifier: Programming Language :: Python :: 3
Classifier: License :: OSI Approved :: MIT License
Classifier: Operating System :: OS Independent
Requires-Python: >=3.7
